iai_helper/__init__.py
iai_helper/core.py
iai_helper/utils.py
iai_helper-1.0.0.dist-info/METADATA
iai_helper-1.0.0.dist-info/WHEEL
iai_helper-1.0.0.dist-info/licenses/LICENSE
iai_helper-1.0.0.dist-info/RECORD
