Metadata-Version: 2.4
Name: iai-helper
Version: 1.0.0
Summary: Intelligent AI Helper – Fast Groq wrapper by YourName
Project-URL: Homepage, https://pypi.org/project/iai-helper
Author-email: Your Name <you@gmail.com>
License: MIT
License-File: LICENSE
Keywords: ai,chatbot,groq,iai,llm
Classifier: License :: OSI Approved :: MIT License
Classifier: Operating System :: OS Independent
Classifier: Programming Language :: Python :: 3
Requires-Python: >=3.8
Requires-Dist: groq>=0.9.0
